railguard/__init__.py
railguard/client.py
railguard_sdk-1.0.0.dist-info/METADATA
railguard_sdk-1.0.0.dist-info/WHEEL
railguard_sdk-1.0.0.dist-info/top_level.txt
railguard_sdk-1.0.0.dist-info/RECORD
