Metadata-Version: 2.4
Name: railguard-sdk
Version: 1.0.0
Summary: Python SDK for RailGuard AI Guardrails
Author-email: RailGuard <support@railguard.io>
License: MIT
Project-URL: Homepage, https://railguard.io
Project-URL: Documentation, https://railguard.io/docs
Project-URL: Repository, https://github.com/railguard/railguard-sdk-python
Keywords: railguard,ai,guardrails,llm,validation
Classifier: Development Status :: 4 - Beta
Classifier: Intended Audience :: Developers
Classifier: License :: OSI Approved :: MIT License
Classifier: Programming Language :: Python :: 3
Classifier: Programming Language :: Python :: 3.7
Classifier: Programming Language :: Python :: 3.8
Classifier: Programming Language :: Python :: 3.9
Classifier: Programming Language :: Python :: 3.10
Classifier: Programming Language :: Python :: 3.11
Requires-Python: >=3.7
Requires-Dist: requests>=2.25.0
